orgformat/__init__.py
orgformat/orgformat.py
orgformat/orgformat_test.py
orgformat-2025.12.13.1.dist-info/licenses/LICENSE.txt
orgformat-2025.12.13.1.dist-info/METADATA
orgformat-2025.12.13.1.dist-info/WHEEL
orgformat-2025.12.13.1.dist-info/top_level.txt
orgformat-2025.12.13.1.dist-info/RECORD
