Metadata-Version: 2.4
Name: orgformat
Version: 2025.12.13.1
Summary: Utility library for providing functions to generate and modify Org mode syntax elements like links, time-stamps, or date-stamps.
Home-page: https://github.com/novoid/orgformat
Download-URL: https://github.com/novoid/orgformat/zipball/master
Author: Karl Voit
Author-email: Karl Voit <tools@Karl-Voit.at>
License:                     GNU GENERAL PUBLIC LICENSE
Project-URL: Homepage, https://github.com/novoid/orgformat
Project-URL: Repository, https://github.com/novoid/orgformat
Project-URL: Issues, https://github.com/novoid/orgformat/issues
Keywords: orgmode,datestamps,timestamps,links
Classifier: Programming Language :: Python :: 3 :: Only
Classifier: Development Status :: 5 - Production/Stable
Classifier: Environment :: Console
Classifier: Intended Audience :: End Users/Desktop
Classifier: License :: OSI Approved :: GNU General Public License (GPL)
Classifier: Operating System :: OS Independent
Requires-Python: >=3.13
License-File: LICENSE.txt
Dynamic: author
Dynamic: download-url
Dynamic: home-page
Dynamic: license-file
